{
  "escritorios": {
    "CANABARRO, NOBERTO ADVOGADOS ASSOCIADOS": "CANABARRO, NOBERTO ADVOGADOS ASSOCIADOS",
    "YURI R. C. BARBOSA SOCIEDADE INDIVIDUAL DE ADVOCACIA": "YURI R. C. BARBOSA SOCIEDADE INDIVIDUAL DE ADVOCACIA",
    "EINLOFT, LOYOLA, CAMARGO, MAINERI ADVOGADOS ASSOCIADOS": "EINLOFT, LOYOLA, CAMARGO, MAINERI ADVOGADOS ASSOCIADOS",
    "DANTAS E GUEDES ADVOGADOS ASSOCIADOS": "DANTAS E GUEDES ADVOGADOS ASSOCIADOS",
    "GIANCARLO FERRENTINI SALEM": "GIANCARLO FERRENTINI SALEM",
    "LEANDRO TONELLO SOCIEDADE INDIVIDUAL DE ADVOCACIA": "LEANDRO TONELLO SOCIEDADE INDIVIDUAL DE ADVOCACIA",
    "Morais & Amorim Advogados Associados": "Morais & Amorim Advogados Associados",
    "MARCELO REVELANTE FERREIRA": "MARCELO REVELANTE FERREIRA",
    "GELSON FERRAREZE SOCIEDADE DE ADVOGADOS": "GELSON FERRAREZE SOCIEDADE DE ADVOGADOS",
    "OSCAR TEIXEIRA DE SIQUEIRA ANDRADE": "OSCAR TEIXEIRA DE SIQUEIRA ANDRADE",
    "ALTAVISTA RIBEIRO SOCIEDADE INDIVIDUAL DE ADVOCACIA": "ALTAVISTA RIBEIRO SOCIEDADE INDIVIDUAL DE ADVOCACIA",
    "BRITTO ARAGAO E SANTANA RIBEIRO": "BRITTO ARAGAO E SANTANA RIBEIRO",
    "MARTINS COSTA E KEUNECKE ADVOGADOS ASSOCIADOS": "MARTINS COSTA E KEUNECKE ADVOGADOS ASSOCIADOS",
    "PERIUS ADVOGADOS ASSOCIADOS": "PERIUS ADVOGADOS ASSOCIADOS",
    "CARVALHO SANTOS E ORCIOLI": "CARVALHO SANTOS E ORCIOLI",
    "DALBONE SOCIEDADE INDIVIDUAL DE ADVOCACIA": "DALBONE SOCIEDADE INDIVIDUAL DE ADVOCACIA",
    "CRIVELLI ADVOGADOS ASSOCIADOS": "CRIVELLI ADVOGADOS ASSOCIADOS",
    "Boldori & Ramos Sociedade de Advogados": "Boldori & Ramos Sociedade de Advogados",
    "JOSÉ TELES BEZERRA JUNIOR": "JOSÉ TELES BEZERRA JUNIOR",
    "CAROLINE ARAUJO GONCALVES": "CAROLINE ARAUJO GONCALVES",
    "DIAS & PYRRHO ADVOGADOS": "DIAS & PYRRHO ADVOGADOS",
    "BARALDI E MELEGA SOCIEDADE DE ADVOGADOS": "BARALDI E MELEGA SOCIEDADE DE ADVOGADOS",
    "COSER, HAAS E TENTARDINI ADVOGADOS": "COSER, HAAS E TENTARDINI ADVOGADOS",
    "CRISTIANINI E INNOCENTE ADVOGADOS": "CRISTIANINI E INNOCENTE ADVOGADOS",
    "Oliveira Coelho Advocacia e Consultoria": "Oliveira Coelho Advocacia e Consultoria",
    "LIMA E PEGOLO ADVOGADOS ASSOCIADOS S": "LIMA E PEGOLO ADVOGADOS ASSOCIADOS S",
    "Ferreira Borges Advogados Associados": "Ferreira Borges Advogados Associados",
    "HIGINO & AMAZONAS ADVOGADOS ASSOCIADOS": "HIGINO & AMAZONAS ADVOGADOS ASSOCIADOS",
    "MOREIRA GARCIA E WEIS ADVOGADOS ASSOCIADOS": "MOREIRA GARCIA E WEIS ADVOGADOS ASSOCIADOS",
    "FLORENTINO OSVALDO DA SILVA": "FLORENTINO OSVALDO DA SILVA",
    "Igor Almeida Lima Advogados Associados": "Igor Almeida Lima Advogados Associados",
    "CECCON & HORDONHO SOCIEDADE DE ADVOGADOS": "CECCON & HORDONHO SOCIEDADE DE ADVOGADOS",
    "CARLOS FELIPE XAVIER CLEROT SOCIEDADE INDIVIDUAL DE ADVOCACIA": "CARLOS FELIPE XAVIER CLEROT SOCIEDADE INDIVIDUAL DE ADVOCACIA",
    "MARCOS ABREU SOCIEDADE INDIVIDUAL DE ADVOCACIA": "MARCOS ABREU SOCIEDADE INDIVIDUAL DE ADVOCACIA",
    "NUNES MARES SOCIEDADE DE ADVOGADOS": "NUNES MARES SOCIEDADE DE ADVOGADOS",
    "YVES MAIA DE ALBUQUERQUE FILHO": "YVES MAIA DE ALBUQUERQUE FILHO",
    "ALEXANDRE FERREIRA SOCIEDADE INDIVIDUAL DE ADVOCACIA": "ALEXANDRE FERREIRA SOCIEDADE INDIVIDUAL DE ADVOCACIA",
    "AMANDA MONTENEGRO CARVALHO": "AMANDA MONTENEGRO CARVALHO",
    "SARAH DORNAS DE PAIVA SOCIEDADE INDIVIDUAL DE ADVOCACIA": "SARAH DORNAS DE PAIVA SOCIEDADE INDIVIDUAL DE ADVOCACIA",
    "Rigoni Advogados Associados": "Rigoni Advogados Associados",
    "PAIVA & PORFIRIO CONSULTORIA JURÍDICA": "PAIVA & PORFIRIO CONSULTORIA JURÍDICA",
    "MOREIRA BRAGA & NETO - ADVOGADOS ASSOCIADOS": "MOREIRA BRAGA & NETO - ADVOGADOS ASSOCIADOS",
    "MACIEIRA, NUNES, ZAGALLO & ADVOGADOS ASSOCIADOS": "MACIEIRA, NUNES, ZAGALLO & ADVOGADOS ASSOCIADOS",
    "ALEXANDRE DOS REIS LIMA SOCIEDADE INDIVIDUAL DE ADVOCACIA": "ALEXANDRE DOS REIS LIMA SOCIEDADE INDIVIDUAL DE ADVOCACIA",
    "Blas Sociedade de Advogados": "Blas Sociedade de Advogados",
    "ALEXANDRE VIEIRA - SOCIEDADE INDIVIDUAL DE ADVOCACIA": "ALEXANDRE VIEIRA - SOCIEDADE INDIVIDUAL DE ADVOCACIA",
    "GALVAO, CABRAL E PIRES ADVOCACIA E CONSULTORIA JURIDICA": "GALVAO, CABRAL E PIRES ADVOCACIA E CONSULTORIA JURIDICA",
    "MARCELO FOGGIATO LICHESKI & ADVOGADOS ASSOCIADOS": "MARCELO FOGGIATO LICHESKI & ADVOGADOS ASSOCIADOS",
    "A. RODRIGUES - SOCIEDADE DE ADVOGADOS": "A. RODRIGUES - SOCIEDADE DE ADVOGADOS",
    "FAZANI SOCIEDADE DE ADVOGADOS": "FAZANI SOCIEDADE DE ADVOGADOS",
    "LEONARDO BISPO FERREIRA": "LEONARDO BISPO FERREIRA",
    "Marcelo Assunçao Advogados Associados": "Marcelo Assunçao Advogados Associados",
    "Walker Tonello Junior e Advogados Associados": "Walker Tonello Junior e Advogados Associados",
    "RUAN CASTRO SOCIEDADE INDIVIDUAL DE ADVOCACIA": "RUAN CASTRO SOCIEDADE INDIVIDUAL DE ADVOCACIA",
    "SAVIO FALCAO SOCIEDADE INDIVIDUAL DE ADVOCACIA": "SAVIO FALCAO SOCIEDADE INDIVIDUAL DE ADVOCACIA",
    "IGOR FELIPE PARAISO MACIEIRA": "IGOR FELIPE PARAISO MACIEIRA",
    "ALICIA RODRIGUEZ SOCIEDADE INDIVIDUAL DE ADVOCACIA": "ALICIA RODRIGUEZ SOCIEDADE INDIVIDUAL DE ADVOCACIA",
    "LUCIANA RIBEIRO SOCIEDADE DE ADVOGADOS": "LUCIANA RIBEIRO SOCIEDADE DE ADVOGADOS",
    "GAUDÊNCIO, MACIEIRA & BAUDEL ADVOGADOS": "GAUDÊNCIO, MACIEIRA & BAUDEL ADVOGADOS",
    "ANDREY LEVI DIOGENES MAGALHÃES SOCIEDADE INDIVIDUAL DE ADVOCACIA": "ANDREY LEVI DIOGENES MAGALHÃES SOCIEDADE INDIVIDUAL DE ADVOCACIA",
    "MARCIAL, PEREIRA & CARVALHO ADVOCACIA": "MARCIAL, PEREIRA & CARVALHO ADVOCACIA",
    "DANIEL SALUME ADVOGADOS": "DANIEL SALUME ADVOGADOS",
    "SOUZA, ABREU E COSTA ADVOGADOS ASSOCIADOS": "SOUZA, ABREU E COSTA ADVOGADOS ASSOCIADOS",
    "ALLAN DOUGLAS OLIVEIRA SOCIEDADE INDIVIDUAL DE ADVOCACIA": "ALLAN DOUGLAS OLIVEIRA SOCIEDADE INDIVIDUAL DE ADVOCACIA",
    "ADVOCACIA MAGALHAES E MAGALHAES": "ADVOCACIA MAGALHAES E MAGALHAES",
    "ALIONI E BRASIL CONSULTORIA ADVOCACIA": "ALIONI E BRASIL CONSULTORIA ADVOCACIA",
    "PAULO ESDRAS MARQUES RAMOS": "PAULO ESDRAS MARQUES RAMOS",
    "NORONHA & FREITAS ADVOGADOS": "NORONHA & FREITAS ADVOGADOS",
    "D. F. RODRIGUES SOCIEDADE INDIVIDUAL DE ADVOCACIA": "D. F. RODRIGUES SOCIEDADE INDIVIDUAL DE ADVOCACIA",
    "MOTTA MELO SOCIEDADE DE ADVOGADOS": "MOTTA MELO SOCIEDADE DE ADVOGADOS",
    "WYNNE E LEITE ADVOGADOS ASSOCIADOS": "WYNNE E LEITE ADVOGADOS ASSOCIADOS",
    "Edson Teodoro Sociedade Individual de Advocacia": "Edson Teodoro Sociedade Individual de Advocacia",
    "ARTHUR DE ARAUJO FERREIRA": "ARTHUR DE ARAUJO FERREIRA",
    "CASSIO ANDRADE ADVOGADOS ASSOCIADOS": "CASSIO ANDRADE ADVOGADOS ASSOCIADOS",
    "MENEZES, PINTO & MARRACINI ADVOCACIA E CONSULTORIA JURIDICA": "MENEZES, PINTO & MARRACINI ADVOCACIA E CONSULTORIA JURIDICA",
    "AVILA, PRADO & LOPES ADVOCACIA": "AVILA, PRADO & LOPES ADVOCACIA",
    "MAGALHAES E CHEGURY ADVOGADOS ASSOCIADOS": "MAGALHAES E CHEGURY ADVOGADOS ASSOCIADOS",
    "DIEGUES, LOPES & RODRIGUES SOCIEDADE DE ADVOGADOS": "DIEGUES, LOPES & RODRIGUES SOCIEDADE DE ADVOGADOS",
    "SIQUEIRA DAVILA FLORES E ADVOGADOS ASSOCIADOS": "SIQUEIRA DAVILA FLORES E ADVOGADOS ASSOCIADOS",
    "TORTUL SOCIEDADE INDIVIDUAL DE ADVOCACIA": "TORTUL SOCIEDADE INDIVIDUAL DE ADVOCACIA",
    "GIL RODRIGUES & WANDERLEY ADVOGADOS": "GIL RODRIGUES & WANDERLEY ADVOGADOS",
    "VITO LEAL PETRUCCI SOCIEDADE INDIVIDUAL DE ADVOCACIA": "VITO LEAL PETRUCCI SOCIEDADE INDIVIDUAL DE ADVOCACIA",
    "Almeida, Nasser & Berbert Fontes Advocacia": "Almeida, Nasser & Berbert Fontes Advocacia",
    "GROSS & KLEIN ADVOCACIA": "GROSS & KLEIN ADVOCACIA",
    "SANCHES E SANCHES GUILHERME SOCIEDADE DE ADVOGADOS": "SANCHES E SANCHES GUILHERME SOCIEDADE DE ADVOGADOS",
    "SENO PETRI ADVOGADOS ASSOCIADOS": "SENO PETRI ADVOGADOS ASSOCIADOS",
    "ARTUNI, FRAZATTI & BONINI SOCIEDADE DE ADVOGADOS": "ARTUNI, FRAZATTI & BONINI SOCIEDADE DE ADVOGADOS",
    "MASSOTE & GUGLIELMELLI SOCIEDADE DE ADVOGADOS": "MASSOTE & GUGLIELMELLI SOCIEDADE DE ADVOGADOS",
    "Morais Cantero Advogados Associados": "Morais Cantero Advogados Associados",
    "JADE ALMEIDA SOCIEDADE INDIVIDUAL DE ADVOCACIA": "JADE ALMEIDA SOCIEDADE INDIVIDUAL DE ADVOCACIA",
    "CLAUDIO MARINHO SOCIEDADE INDIVIDUAL DE ADVOCACIA": "CLAUDIO MARINHO SOCIEDADE INDIVIDUAL DE ADVOCACIA",
    "Boaventura Bernardes e Mattos Sociedade de Advogados": "Boaventura Bernardes e Mattos Sociedade de Advogados",
    "WEYL, FREITAS, KAHWAGE DAVID, VIEIRA E BOTELHO, ADVOGADOS ASSOCIADOS": "WEYL, FREITAS, KAHWAGE DAVID, VIEIRA E BOTELHO, ADVOGADOS ASSOCIADOS",
    "ROMEIRO DOS SANTOS SOCIEDADE INDIVIDUAL DE ADVOCACIA": "ROMEIRO DOS SANTOS SOCIEDADE INDIVIDUAL DE ADVOCACIA",
    "PAULO ROBERTO SANTOS ADVOGADOS ASSOCIADOS": "PAULO ROBERTO SANTOS ADVOGADOS ASSOCIADOS",
    "GUERRA E GUERRA SOCIEDADE DE ADVOGADOS": "GUERRA E GUERRA SOCIEDADE DE ADVOGADOS",
    "ADELCIO ARAUJO SOCIEDADE DE ADVOGADOS": "ADELCIO ARAUJO SOCIEDADE DE ADVOGADOS",
    "LEANDRO PAIM RIOS ADVOGADOS ASSOCIADOS": "LEANDRO PAIM RIOS ADVOGADOS ASSOCIADOS",
    "MIGUEL GLASHORESTER SEVERO": "MIGUEL GLASHORESTER SEVERO",
    "BASILE ADVOGADOS ASSOCIADOS": "BASILE ADVOGADOS ASSOCIADOS",
    "TONELLO - SOCIEDADE INDIVIDUAL DE ADVOCACIA": "TONELLO - SOCIEDADE INDIVIDUAL DE ADVOCACIA",
    "VARJAL & ADVOGADOS ASSOCIADOS": "VARJAL & ADVOGADOS ASSOCIADOS",
    "COLONI & WENDT ADVOGADOS": "COLONI & WENDT ADVOGADOS",
    "PEDRO PAULO PEDROSA - ADVOGADOS ASSOCIADOS": "PEDRO PAULO PEDROSA - ADVOGADOS ASSOCIADOS",
    "CARMONA ADVOGADOS ASSOCIADOS": "CARMONA ADVOGADOS ASSOCIADOS",
    "FRANCO E CELLI": "FRANCO E CELLI",
    "LANNES E LANNES SOCIEDADE DE ADVOGADOS": "LANNES E LANNES SOCIEDADE DE ADVOGADOS",
    "Pamplona e Honjoya Sociedade de Advogados": "Pamplona e Honjoya Sociedade de Advogados",
    "MARTINS DE QUADROS ADVOGADOS ASSOCIADOS": "MARTINS DE QUADROS ADVOGADOS ASSOCIADOS",
    "ANDERSON PATRICIO ADVOGADOS ASSOCIADOS": "ANDERSON PATRICIO ADVOGADOS ASSOCIADOS",
    "ROMAN ADVOGADOS ASSOCIADOS": "ROMAN ADVOGADOS ASSOCIADOS",
    "ADVOCACIA BORGES": "ADVOCACIA BORGES",
    "PITANGA & PITANGA SOCIEDADE DE ADVOGADOS": "PITANGA & PITANGA SOCIEDADE DE ADVOGADOS",
    "CALDEIRA BRANT SOCIEDADE DE ADVOGADOS": "CALDEIRA BRANT SOCIEDADE DE ADVOGADOS",
    "BRAGA LINCOLN ADVOGADOS": "BRAGA LINCOLN ADVOGADOS",
    "ESCRITÓRIO DE ADVOCACIA PERRINI ADVOGADOS": "ESCRITÓRIO DE ADVOCACIA PERRINI ADVOGADOS",
    "CARVALHO, VASCONCELLOS & ASSOCIADOS - SOCIEDADE DE ADVOGADOS": "CARVALHO, VASCONCELLOS & ASSOCIADOS - SOCIEDADE DE ADVOGADOS",
    "FELIPE NESS & SÉRGIO MARTINS ADVOGADOS ASSOCIADOS": "FELIPE NESS & SÉRGIO MARTINS ADVOGADOS ASSOCIADOS",
    "BSJ ADVOCACIA ESPECIALIZADA": "BSJ ADVOCACIA ESPECIALIZADA",
    "MUSIELLO E SANTANA ADVOCACIA": "MUSIELLO E SANTANA ADVOCACIA",
    "SAMUEL DIAS DE MOURA": "SAMUEL DIAS DE MOURA",
    "MARCELO GIOVANI BATISTA MAIA - SOCIEDADE INDIVIDUAL DE ADVOCACIA": "MARCELO GIOVANI BATISTA MAIA - SOCIEDADE INDIVIDUAL DE ADVOCACIA",
    "MATHEUS CALDAS SOCIEDADE INDIVIDUAL DE ADVOCACIA": "MATHEUS CALDAS SOCIEDADE INDIVIDUAL DE ADVOCACIA",
    "GARCIA FILHO ADVOGADOS ASSOCIADOS": "GARCIA FILHO ADVOGADOS ASSOCIADOS",
    "MÔNICA BRUNETTO - SOCIEDADE INDIVIDUAL DE ADVOCACIA": "MÔNICA BRUNETTO - SOCIEDADE INDIVIDUAL DE ADVOCACIA",
    "IULLY FREIRE GARCIA DE OLIVEIRA SOCIEDADE INDIVIDUAL DE ADVOCACIA": "IULLY FREIRE GARCIA DE OLIVEIRA SOCIEDADE INDIVIDUAL DE ADVOCACIA",
    "R. PALMA SOCIEDADE INDIVIDUAL DE ADVOCACIA": "R. PALMA SOCIEDADE INDIVIDUAL DE ADVOCACIA",
    "Jhonatan Pinati Sociedade Individual de Advocacia": "Jhonatan Pinati Sociedade Individual de Advocacia",
    "JACQUELINE GASPAR DE OLIVEIRA CARNEIRO": "JACQUELINE GASPAR DE OLIVEIRA CARNEIRO",
    "ALENCAR & MAEHLER ADVOGADOS": "ALENCAR & MAEHLER ADVOGADOS",
    "MORELLI ADVOGADOS ASSOCIADOS": "MORELLI ADVOGADOS ASSOCIADOS",
    "MARY COHEN SOCIEDADE INDIVIDUAL DE ADVOCACIA": "MARY COHEN SOCIEDADE INDIVIDUAL DE ADVOCACIA",
    "FALCAO & RAMOS SOCIEDADE DE ADVOGADOS": "FALCAO & RAMOS SOCIEDADE DE ADVOGADOS",
    "Barros, Martins advocacia e consultoria": "Barros, Martins advocacia e consultoria",
    "GABRIEL MALHEIROS ADVOGADOS": "GABRIEL MALHEIROS ADVOGADOS",
    "MICHELLY PEDROSA SOCIEDADE DE ADVOGADOS": "MICHELLY PEDROSA SOCIEDADE DE ADVOGADOS",
    "SARAIVA E CASTRO ADVOCACIA ESPECIALIZADA": "SARAIVA E CASTRO ADVOCACIA ESPECIALIZADA",
    "MOURA E SILVA SOCIEDADE INDIVIDUAL DE ADVOCACIA": "MOURA E SILVA SOCIEDADE INDIVIDUAL DE ADVOCACIA",
    "Duraes & Maia Advocacia e Consultoria": "Duraes & Maia Advocacia e Consultoria",
    "BÁRBARA HERRERA DE SOUZA": "BÁRBARA HERRERA DE SOUZA",
    "PARREIRA DAVANZO GARCIA SOCIEDADE DE ADVOGADOS": "PARREIRA DAVANZO GARCIA SOCIEDADE DE ADVOGADOS",
    "CAPANEMA PINHEIRO & RENNÓ SOCIEDADE DE ADVOGADOS": "CAPANEMA PINHEIRO & RENNÓ SOCIEDADE DE ADVOGADOS",
    "Lacerda, Mattei e Bulhões Advogados Associados": "Lacerda, Mattei e Bulhões Advogados Associados",
    "LEONARDO AUGUSTO ALENCAR RENAULT": "LEONARDO AUGUSTO ALENCAR RENAULT",
    "RICARDO SANCHES GUILHERME SOCIEDADE INDIVIDUAL DE ADVOCACIA": "RICARDO SANCHES GUILHERME SOCIEDADE INDIVIDUAL DE ADVOCACIA",
    "FETT ADVOGADOS ASSOCIADOS": "FETT ADVOGADOS ASSOCIADOS",
    "ANTONIO CARLOS DE MATOS SOCIEDADE INDIVIDUAL DE ADVOCACIA": "ANTONIO CARLOS DE MATOS SOCIEDADE INDIVIDUAL DE ADVOCACIA",
    "CATIA SIMONE ARTEIRO": "CATIA SIMONE ARTEIRO",
    "VIRGINIA PORTO SOCIEDADE INDIVIDUAL DE ADVOCACIA": "VIRGINIA PORTO SOCIEDADE INDIVIDUAL DE ADVOCACIA",
    "Raquel Alves Advogados Associados": "Raquel Alves Advogados Associados",
    "RENATO SHINTAKU ADVOGADOS ASSOCIADOS": "RENATO SHINTAKU ADVOGADOS ASSOCIADOS",
    "GONÇALVES, AUACHE, SALVADOR, ALLAN & MENDONÇA ADVOCACIA": "GONÇALVES, AUACHE, SALVADOR, ALLAN & MENDONÇA ADVOCACIA",
    "DE CASTRO & ADVOGADOS ASSOCIADOS": "DE CASTRO & ADVOGADOS ASSOCIADOS",
    "Kehl E Camargo Advogados Associados": "Kehl E Camargo Advogados Associados",
    "PIRES DE SOUZA SOCIEDADE INDIVIDUAL DE ADVOCACIA": "PIRES DE SOUZA SOCIEDADE INDIVIDUAL DE ADVOCACIA",
    "ERICO JOSÉ MARTINS DA SILVA SOCIEDADE INDIVIDUAL DE ADVOCACIA": "ERICO JOSÉ MARTINS DA SILVA SOCIEDADE INDIVIDUAL DE ADVOCACIA",
    "MELO E ISAAC ADVOGADOS": "MELO E ISAAC ADVOGADOS",
    "ROCHA E QUEIROZ ADVOGADOS": "ROCHA E QUEIROZ ADVOGADOS",
    "SALVADOR FERREIRA SOCIEDADE INDIVIDUAL DE ADVOCACIA": "SALVADOR FERREIRA SOCIEDADE INDIVIDUAL DE ADVOCACIA",
    "Glomb Advogados Associados": "Glomb Advogados Associados",
    "STUPPELLO, AZEVEDO E GUARANA ADVOGADOS ASSOCIADOS": "STUPPELLO, AZEVEDO E GUARANA ADVOGADOS ASSOCIADOS",
    "SARAH MARGARETTE BEZERRA PINTO": "SARAH MARGARETTE BEZERRA PINTO",
    "BRUNO FISCHER FRAIZ DE MORAIS SOCIEDADE INDIVIDUAL DE ADVOCACIA": "BRUNO FISCHER FRAIZ DE MORAIS SOCIEDADE INDIVIDUAL DE ADVOCACIA",
    "BERNARDI & BERNARDI ADVOGADOS ASSOCIADOS": "BERNARDI & BERNARDI ADVOGADOS ASSOCIADOS",
    "AUTRAN NUNES E TEIXEIRA ADVOGADOS": "AUTRAN NUNES E TEIXEIRA ADVOGADOS",
    "ARGENTON E QUEIROZ ADVOGADOS ASSOCIADOS": "ARGENTON E QUEIROZ ADVOGADOS ASSOCIADOS",
    "DAYANE SOARES SHIOYA": "DAYANE SOARES SHIOYA",
    "MURI & NEGRISOLI ADVOGADOS ASSOCIADOS": "MURI & NEGRISOLI ADVOGADOS ASSOCIADOS",
    "DANIELA SIQUEIRA VALADARES": "DANIELA SIQUEIRA VALADARES",
    "MAYCON SIMOES CARDOSO, REGIS ROBERTO DA SILVA, ANDERSON SANTOS DA SILVA & ADVOGADOS ASSOCIADOS": "MAYCON SIMOES CARDOSO, REGIS ROBERTO DA SILVA, ANDERSON SANTOS DA SILVA & ADVOGADOS ASSOCIADOS",
    "THIAGO LEANDRO BARBOSA SOCIEDADE INDIVIDUAL DE ADVOCACIA": "THIAGO LEANDRO BARBOSA SOCIEDADE INDIVIDUAL DE ADVOCACIA",
    "LIMA & VILANI ADVOGADOS ASSOCIADOS": "LIMA & VILANI ADVOGADOS ASSOCIADOS",
    "FRANCISCO MONTENEGRO JUNIOR SOCIEDADE INDIVIDUAL DE  ADVOCACIA": "FRANCISCO MONTENEGRO JUNIOR SOCIEDADE INDIVIDUAL DE  ADVOCACIA",
    "Tomé Pereira & Sandro Miranda": "Tomé Pereira & Sandro Miranda",
    "CARVALHO, SILVA E ALMEIDA ADVOGADOS ASSOCIADOS": "CARVALHO, SILVA E ALMEIDA ADVOGADOS ASSOCIADOS",
    "BRUNA PEREIRA DOS SANTOS": "BRUNA PEREIRA DOS SANTOS",
    "AMORIM E MAIA ADVOGADOS ASSOCIADOS": "AMORIM E MAIA ADVOGADOS ASSOCIADOS",
    "Cani Bella Rosa Sociedade Individual de Advocacia": "Cani Bella Rosa Sociedade Individual de Advocacia",
    "SHYNAIDE MAFRA SOCIEDADE INDIVIDUAL DE ADVOCACIA": "SHYNAIDE MAFRA SOCIEDADE INDIVIDUAL DE ADVOCACIA",
    "VINICIUS FERREIRA SOCIEDADE INDIVIDUAL DE ADVOCACIA": "VINICIUS FERREIRA SOCIEDADE INDIVIDUAL DE ADVOCACIA",
    "BERNARDINO ADVOGADOS": "BERNARDINO ADVOGADOS",
    "CESAR PEREIRA & ADVOGADOS ASSOCIADOS": "CESAR PEREIRA & ADVOGADOS ASSOCIADOS",
    "PORTO E SEVERGNINI ADVOGADOS ASSOCIADOS": "PORTO E SEVERGNINI ADVOGADOS ASSOCIADOS",
    "GRACO COUTINHO SOCIEDADE DE ADVOGADOS": "GRACO COUTINHO SOCIEDADE DE ADVOGADOS",
    "MELO PRATES E OLIVEIRA - ADVOGADOS ASSOCIADOS": "MELO PRATES E OLIVEIRA - ADVOGADOS ASSOCIADOS",
    "AMORIM E GUERRA ADVOGADOS ASSOCIADOS": "AMORIM E GUERRA ADVOGADOS ASSOCIADOS",
    "SALIM SAYAR & FERREIRA ADVOGADOS ASSOCIADOS": "SALIM SAYAR & FERREIRA ADVOGADOS ASSOCIADOS",
    "BOLIVAR, MOURA & CASTRO SOCIEDADE DE ADVOGADOS": "BOLIVAR, MOURA & CASTRO SOCIEDADE DE ADVOGADOS",
    "VITOR RODRIGUES MOURA SOCIEDADE DE ADVOGADOS": "VITOR RODRIGUES MOURA SOCIEDADE DE ADVOGADOS",
    "GLAUCO RODOLFO FONSECA DE SENA": "GLAUCO RODOLFO FONSECA DE SENA",
    "SOUZA SOARES & SILVA ADVOCACIA": "SOUZA SOARES & SILVA ADVOCACIA",
    "FLEITH, ZILLI, QUADROS & GOES SOCIEDADE DE ADVOGADOS": "FLEITH, ZILLI, QUADROS & GOES SOCIEDADE DE ADVOGADOS",
    "RAFAEL CAMARA MENDINA": "RAFAEL CAMARA MENDINA",
    "EDUARDO MOTA SOCIEDADE INDIVIDUAL DE ADVOCACIA": "EDUARDO MOTA SOCIEDADE INDIVIDUAL DE ADVOCACIA",
    "DANIELA ZAMBAO ABDIAN": "DANIELA ZAMBAO ABDIAN",
    "MELONI ADVOGADOS ASSOCIADOS": "MELONI ADVOGADOS ASSOCIADOS",
    "Bosquerolli e Silva Advogados Associados": "Bosquerolli e Silva Advogados Associados",
    "MARIA DE FATIMA BEZERRA": "MARIA DE FATIMA BEZERRA",
    "GUSTAVO ALVES DE LIMA SOCIEADE INDIVIDUAL DE ADVOCACIA": "GUSTAVO ALVES DE LIMA SOCIEADE INDIVIDUAL DE ADVOCACIA",
    "FILIPE LEITE DE MELO FERREIRA CANÇADO SOCIEDADE INDIVIDUAL DE ADVOCACIA": "FILIPE LEITE DE MELO FERREIRA CANÇADO SOCIEDADE INDIVIDUAL DE ADVOCACIA",
    "Sidenilson Fontes Sociedade Individual de Advocacia": "Sidenilson Fontes Sociedade Individual de Advocacia",
    "GOFFREDO SOCIEDADE DE ADVOGADOS": "GOFFREDO SOCIEDADE DE ADVOGADOS",
    "ARRABAÇA & ADVOGADOS ASSOCIADOS": "ARRABAÇA & ADVOGADOS ASSOCIADOS",
    "Maxwell Estrela Araujo Dantas": "Maxwell Estrela Araujo Dantas",
    "RENATO RUA DE ALMEIDA": "RENATO RUA DE ALMEIDA",
    "SOTERIO SOCIEDADE INDIVIDUAL DE ADVOCACIA": "SOTERIO SOCIEDADE INDIVIDUAL DE ADVOCACIA",
    "ABREU & BRITO GOMES ADVOGADOS ASSOCIADOS": "ABREU & BRITO GOMES ADVOGADOS ASSOCIADOS",
    "FRANCIELA GUILARDE SOCIEDADE INDIVIDUAL DE ADVOCACIA": "FRANCIELA GUILARDE SOCIEDADE INDIVIDUAL DE ADVOCACIA",
    "PETRUCCIO PAIVA SOCIEDADE INDIVIDUAL DE ADVOCACIA": "PETRUCCIO PAIVA SOCIEDADE INDIVIDUAL DE ADVOCACIA",
    "JORGE COSTA SOCIEDADE INDIVIDUAL DE ADVOCACIA": "JORGE COSTA SOCIEDADE INDIVIDUAL DE ADVOCACIA",
    "Diogo Moraes de Mello Sociedade Individual de Advocacia": "Diogo Moraes de Mello Sociedade Individual de Advocacia",
    "SOARES BASTOS & CAVALCANTE ADVOCACIA": "SOARES BASTOS & CAVALCANTE ADVOCACIA",
    "PEDRO EDUARDO GOMES CAVALCANTE VIEIRA": "PEDRO EDUARDO GOMES CAVALCANTE VIEIRA",
    "GILMAR MOURA DOS SANTOS - Sem escritório": "GILMAR MOURA DOS SANTOS - Sem escritório",
    "THIAGO PAES FONSECA DANTAS SOCIEDADE INDIVIDUAL DE ADVOCACIA": "THIAGO PAES FONSECA DANTAS SOCIEDADE INDIVIDUAL DE ADVOCACIA",
    "El Kadri Advogados Associados": "El Kadri Advogados Associados",
    "PAULO KATSUMI FUGI ADVOGADOS ASSOCIADOS": "PAULO KATSUMI FUGI ADVOGADOS ASSOCIADOS",
    "MARIANA RAMOS PAIVA SOBREIRA": "MARIANA RAMOS PAIVA SOBREIRA",
    "Mainenti, Grossi & Froes de Aguilar Sociedade de Advogados": "Mainenti, Grossi & Froes de Aguilar Sociedade de Advogados",
    "SOUSA MALCHER ADVOCACIA": "SOUSA MALCHER ADVOCACIA",
    "ADERBAL PINTO JUNIOR": "ADERBAL PINTO JUNIOR",
    "FERREIRA SALU SOCIEDADE INDIVIDUAL DE ADVOCACIA": "FERREIRA SALU SOCIEDADE INDIVIDUAL DE ADVOCACIA",
    "PINHEIRO & OLIVEIRA ADVOGADOS ASSOCIADOS": "PINHEIRO & OLIVEIRA ADVOGADOS ASSOCIADOS",
    "SOUZA & SOUZA ADVOGADOS ASSOCIADOS": "SOUZA & SOUZA ADVOGADOS ASSOCIADOS",
    "PHILIP RAMON GARCIA DE ABRANTES": "PHILIP RAMON GARCIA DE ABRANTES",
    "AMORIM & AZEVEDO ADVOGADOS ASSOCIADOS": "AMORIM & AZEVEDO ADVOGADOS ASSOCIADOS",
    "SALGADO E LOUCAO ADVOGADOS": "SALGADO E LOUCAO ADVOGADOS",
    "ARAUJO E FILHOS - ADVOGADOS ASSOCIADOS": "ARAUJO E FILHOS - ADVOGADOS ASSOCIADOS",
    "KLAUS BAYER RIESEMBERG SOCIEDADE INDIVIDUAL DE ADVOCACIA": "KLAUS BAYER RIESEMBERG SOCIEDADE INDIVIDUAL DE ADVOCACIA",
    "Jefferson Franck da Silva Cruz": "Jefferson Franck da Silva Cruz",
    "RODRIGO DABUL TORRES": "RODRIGO DABUL TORRES",
    "PATRIOTA & COUTINHO ADVOGADOS ASSOCIADOS": "PATRIOTA & COUTINHO ADVOGADOS ASSOCIADOS",
    "MÁXIMO TEODORO & OLIVEIRA SOCIEDADE DE ADVOGADOS": "MÁXIMO TEODORO & OLIVEIRA SOCIEDADE DE ADVOGADOS",
    "Gustavo Matheus Dias De Souza Sociedade individual De Advocacia": "Gustavo Matheus Dias De Souza Sociedade individual De Advocacia",
    "Leonardo Cesar Gomes Garcia Sociedade Individual de Advocacia": "Leonardo Cesar Gomes Garcia Sociedade Individual de Advocacia",
    "RODRIGUES E MOURA SOCIEDADE DE ADVOGADOS": "RODRIGUES E MOURA SOCIEDADE DE ADVOGADOS",
    "FERNANDA GABRIELA RISERIO BRITO": "FERNANDA GABRIELA RISERIO BRITO",
    "ANDRE FERRARI SOCIEDADE DE ADVOGADOS": "ANDRE FERRARI SOCIEDADE DE ADVOGADOS",
    "PREVEDELLO, TOLDO E ZAMBONIN SOCIEDADE DE ADVOGADOS": "PREVEDELLO, TOLDO E ZAMBONIN SOCIEDADE DE ADVOGADOS",
    "MARTINS, BUCH & SATO ADVOGADOS ASSOCIADOS": "MARTINS, BUCH & SATO ADVOGADOS ASSOCIADOS",
    "Fabio Rodigheri Sociedade Individual de Advocacia": "Fabio Rodigheri Sociedade Individual de Advocacia",
    "JEAN MARK MENEZES CORREA SOCIEDADE INDIVIDUAL DE ADVOCACIA": "JEAN MARK MENEZES CORREA SOCIEDADE INDIVIDUAL DE ADVOCACIA",
    "D`AVILA FERNANDES ADVOGADOS ASSOCIADOS": "D`AVILA FERNANDES ADVOGADOS ASSOCIADOS",
    "ALLAN GOMES FERREIRA SOCIEDADE INDIVIDUAL DE ADVOCACIA": "ALLAN GOMES FERREIRA SOCIEDADE INDIVIDUAL DE ADVOCACIA",
    "ESPEDITO FONSECA SOCIEDADE INDIVIDUAL DE ADVOCACIA": "ESPEDITO FONSECA SOCIEDADE INDIVIDUAL DE ADVOCACIA",
    "URBANO VITALINO ADVOGADOS": "URBANO VITALINO ADVOGADOS",
    "EDER CAVALCANTE RODRIGUES": "EDER CAVALCANTE RODRIGUES",
    "FERNANDO DE FAVERE SOCIEDADE INDIVIDUAL DE ADVOCACIA": "FERNANDO DE FAVERE SOCIEDADE INDIVIDUAL DE ADVOCACIA",
    "FERRAREZE E FREITAS ADVOGADOS ASSOCIADOS": "FERRAREZE E FREITAS ADVOGADOS ASSOCIADOS",
    "STAUB ADVOGADOS ASSOCIADOS": "STAUB ADVOGADOS ASSOCIADOS",
    "CARLOS GABINO DE SOUSA JUNIOR": "CARLOS GABINO DE SOUSA JUNIOR",
    "SANGLARD, REGGIANI & FERREIRA SOCIEDADE DE ADVOGADOS": "SANGLARD, REGGIANI & FERREIRA SOCIEDADE DE ADVOGADOS",
    "CARVALHO E GIL RODRIGUES SOCIEDADE ADVOGADOS": "CARVALHO E GIL RODRIGUES SOCIEDADE ADVOGADOS",
    "Klafke & Advogados Associados": "Klafke & Advogados Associados",
    "HOERLLE AMÉRICO E MARTINS ADVOCACIA S/S": "HOERLLE AMÉRICO E MARTINS ADVOCACIA S/S",
    "SCHERER & BACALTCHUK ADVOGADOS": "SCHERER & BACALTCHUK ADVOGADOS",
    "ROSILDA MARIA DOS SANTOS SOCIEDADE INDIVIDUAL DE ADVOCACIA": "ROSILDA MARIA DOS SANTOS SOCIEDADE INDIVIDUAL DE ADVOCACIA",
    "GABRIEL YARED FORTE ADVOGADOS ASSOCIADOS": "GABRIEL YARED FORTE ADVOGADOS ASSOCIADOS",
    "HELIO DA SILVA E AGUSTINHO SOCIEDADE DE ADVOGADOS": "HELIO DA SILVA E AGUSTINHO SOCIEDADE DE ADVOGADOS",
    "ANDRÉ SILVA SANTOS DE CARVALHO SOCIEDADE INDIVIDUAL DE ADVOCACIA": "ANDRÉ SILVA SANTOS DE CARVALHO SOCIEDADE INDIVIDUAL DE ADVOCACIA",
    "MIGUEL MENDES SOCIEDADE INDIVIDUAL DE ADVOCACIA": "MIGUEL MENDES SOCIEDADE INDIVIDUAL DE ADVOCACIA",
    "Baruffi Advogados Associados S/S": "Baruffi Advogados Associados S/S",
    "ITALO ARIEL MORBIDELLI SOCIEDADE INDIVIDUAL DE ADVOCACIA": "ITALO ARIEL MORBIDELLI SOCIEDADE INDIVIDUAL DE ADVOCACIA",
    "BORBA & KARSBURG ADVOGADOS ASSOCIADOS": "BORBA & KARSBURG ADVOGADOS ASSOCIADOS",
    "Granero Pereira Advogados Associados": "Granero Pereira Advogados Associados",
    "SPERB ADVOGADOS ASSOCIADOS": "SPERB ADVOGADOS ASSOCIADOS",
    "RODRIGUES LEITE & BONAVITA ADVOGADOS": "RODRIGUES LEITE & BONAVITA ADVOGADOS",
    "FERRAZ - SOCIEDADE INDIVIDUAL DE ADVOCACIA": "FERRAZ - SOCIEDADE INDIVIDUAL DE ADVOCACIA",
    "ADRIANA FRANCA DA SILVA": "ADRIANA FRANCA DA SILVA",
    "L. RIBEIRO SOCIEDADE INDIVIDUAL DE ADVOCACIA": "L. RIBEIRO SOCIEDADE INDIVIDUAL DE ADVOCACIA",
    "FEITOSA & NOVAIS ADVOGADOS ASSOCIADOS": "FEITOSA & NOVAIS ADVOGADOS ASSOCIADOS",
    "CLARISSA COSTA SOCIEDADE INDIVIDUAL DE ADVOCACIA": "CLARISSA COSTA SOCIEDADE INDIVIDUAL DE ADVOCACIA",
    "RAFAEL DE ANDRADE MENDES": "RAFAEL DE ANDRADE MENDES",
    "VALDI JUNIOR SOCIEDADE INDIVIDUAL DE ADVOCACIA": "VALDI JUNIOR SOCIEDADE INDIVIDUAL DE ADVOCACIA",
    "PALMIRO NOVELI TORRES DA FONSECA FILHO": "PALMIRO NOVELI TORRES DA FONSECA FILHO",
    "MOURA, NAKANO, SOUZA E PEREIRA SOCIEDADE DE ADVOGADOS": "MOURA, NAKANO, SOUZA E PEREIRA SOCIEDADE DE ADVOGADOS",
    "LIMA ADVOGADOS ASSOCIADOS": "LIMA ADVOGADOS ASSOCIADOS",
    "VALMOR ANTUNES DE FREITAS": "VALMOR ANTUNES DE FREITAS",
    "Nasser Ahmad Allan": "Nasser Ahmad Allan"
  },
  "total": 279
}
